ThemeTkinter/Core.py
ThemeTkinter/InstallDepend.py
ThemeTkinter/__init__.py
ThemeTkinter-0.0.3.dist-info/LICENSE
ThemeTkinter-0.0.3.dist-info/METADATA
ThemeTkinter-0.0.3.dist-info/WHEEL
ThemeTkinter-0.0.3.dist-info/top_level.txt
ThemeTkinter-0.0.3.dist-info/RECORD
