Metadata-Version: 2.1
Name: ThemeTkinter
Version: 0.0.3
Summary: With beautiful theme tkinter package.
Home-page: https://github.com/xiaocaicai-github/ThemeTkinter
Author: Xiaocaicai
Author-email: xiaocaicai_email@sina.com
License: UNKNOWN
Platform: UNKNOWN
Classifier: Programming Language :: Python :: 3
Classifier: License :: OSI Approved :: MIT License
Classifier: Operating System :: OS Independent
Requires-Python: >=3.4.0
License-File: LICENSE
